lite_llm_client/__init__.py
lite_llm_client/_anthropic_client.py
lite_llm_client/_config.py
lite_llm_client/_gemini_client.py
lite_llm_client/_http_sse.py
lite_llm_client/_interfaces.py
lite_llm_client/_lite_llm_client.py
lite_llm_client/_openai_client.py
lite_llm_client/_otel_tracer.py
lite_llm_client/_tracer.py
lite_llm_client/_types.py
lite_llm_client-0.2.0.dist-info/METADATA
lite_llm_client-0.2.0.dist-info/WHEEL
lite_llm_client-0.2.0.dist-info/top_level.txt
lite_llm_client-0.2.0.dist-info/RECORD
