Metadata-Version: 2.2
Name: lite-llm-client
Version: 0.2.0
Summary: A small example package
Author-email: lovian <belovian@gmail.com>
Project-URL: Homepage, https://github.com/eususu/lite-llm-client
Classifier: Programming Language :: Python :: 3
Classifier: License :: OSI Approved :: MIT License
Classifier: Operating System :: OS Independent
Requires-Python: >=3.8
Requires-Dist: requests
Requires-Dist: python-dotenv
Requires-Dist: pydantic
Provides-Extra: dev
Requires-Dist: black; extra == "dev"
Requires-Dist: bumpver; extra == "dev"
Requires-Dist: isort; extra == "dev"
Requires-Dist: pip-tools; extra == "dev"
Requires-Dist: pytest; extra == "dev"
